{
  "cli": {
    "appVersionSource": "remote",
    "version": ">= 5.0.0"
  },
  "build": {
    "development": {
      "developmentClient": true,
      "distribution": "internal",
      "env": {
        "EXPO_PUBLIC_RELEASE_CHANNEL": "development"
      },
      "ios": {
        "resourceClass": "m-medium"
      },
      "android": {
        "buildType": "apk"
      }
    },
    "preview": {
      "developmentClient": false,
      "distribution": "internal",
      "env": {
        "EXPO_PUBLIC_RELEASE_CHANNEL": "preview"
      },
      "ios": {
        "resourceClass": "m-medium"
      },
      "android": {
        "buildType": "apk"
      }
    },
    "production": {
      "developmentClient": false,
      "distribution": "store",
      "env": {
        "EXPO_PUBLIC_RELEASE_CHANNEL": "production"
      },
      "ios": {
        "resourceClass": "m-medium"
      },
      "android": {
        "buildType": "app-bundle",
        "gradleCommand": ":app:bundleRelease"
      }
    }
  },
  "submit": {
    "preview": {
      "ios": {
        "ascAppId": "6751146458",
        "companyName": "Braveheart Innovations",
        "sku": "com.braveheartinnovations.debateai"
      },
      "android": {
        "track": "internal"
      }
    },
    "production": {
      "ios": {
        "ascAppId": "6751146458",
        "companyName": "Braveheart Innovations",
        "sku": "com.braveheartinnovations.debateai"
      },
      "android": {
        "track": "production"
      }
    }
  }
}